mlops/__init__.py
mlops/cli.py
mlops/api/__init__.py
mlops/api/datasource/__init__.py
mlops/api/datasource/commands.py
mlops/tools/__init__.py
mlops/tools/commands.py
mlops/tools/models/__init__.py
mlops/tools/models/converter.py
elemeno_mlops_cli-0.0.4.dist-info/METADATA
elemeno_mlops_cli-0.0.4.dist-info/WHEEL
elemeno_mlops_cli-0.0.4.dist-info/entry_points.txt
elemeno_mlops_cli-0.0.4.dist-info/top_level.txt
elemeno_mlops_cli-0.0.4.dist-info/RECORD
