Metadata-Version: 2.1
Name: elemeno-mlops-cli
Version: 0.0.4
Summary: A CLI with useful commands for interacting with Elemeno ML Ops
Home-page: https://github.com/elemeno-ai/mlops-cli
Author: Lucas Bonatto Miguel
Author-email: lucas@elemeno.ai
License: BSD
Platform: any
Classifier: Development Status :: 4 - Beta
Classifier: Environment :: Console
Classifier: Intended Audience :: Developers
Classifier: License :: OSI Approved :: BSD License
Classifier: Operating System :: POSIX
Classifier: Operating System :: MacOS
Classifier: Operating System :: Unix
Classifier: Operating System :: Microsoft :: Windows
Classifier: Programming Language :: Python
Classifier: Programming Language :: Python :: 2
Classifier: Programming Language :: Python :: 3
Classifier: Topic :: Software Development :: Libraries :: Python Modules
Requires-Dist: click
Requires-Dist: elemeno-ai-sdk (==0.1.0)
